<?xml version="1.0" encoding="UTF-8"?>
<skin version="0.2">
	<title xml:lang="ko">Sketchbook5</title>
	<description xml:lang="ko">Sketchbook5 게시판 스킨에 대응합니다.</description>
	<version>1.0</version>
	<date>2014-07-20</date>
	<author email_address="contact@ajaxboard.co.kr" link="http://www.ajaxboard.co.kr/">
		<name xml:lang="ko">이즈야</name>
		<name xml:lang="en">ISIZU</name>
		<name xml:lang="jp">イズヤ</name>
	</author>
	<extra_vars>
		<var name="animatetime" type="text">
			<title xml:lang="ko">애니메이션 실행 시간</title>
			<description xml:lang="ko">애니메이션 효과를 사용할 때 지속될 시간을 입력합니다. 초 단위로 입력합니다.</description>
		</var>
		<var name="push_notify_text" type="textarea">
			<title xml:lang="ko">푸시 알림</title>
			<description xml:lang="ko">푸시 알림을 받는 회원에게 보여질 메시지를 입력합니다. %MESSAGE% 구분자를 사용할 수 있습니다.</description>
		</var>
		<var name="document_notify_text" type="textarea">
			<title xml:lang="ko">게시글 알림</title>
			<description xml:lang="ko">게시글 알림을 받는 회원에게 보여질 메시지를 입력합니다. %DOCUMENT_SRL%, %TITLE%, %CONTENT%, %NICKNAME% 구분자를 사용할 수 있습니다.</description>
		</var>
		<var name="comment_notify_text" type="textarea">
			<title xml:lang="ko">댓글 알림</title>
			<description xml:lang="ko">댓글 알림을 받는 회원에게 보여질 메시지를 입력합니다. %DOCUMENT_SRL%, %COMMENT_SRL%, %CONTENT%, %NICKNAME% 구분자를 사용할 수 있습니다.</description>
		</var>
	</extra_vars>
</skin>